{
    "me_no_target": "$",
    "me_self": "You hold your chin in your hand and begin to think to yourself...",
    "actor_room": "$n sits back and begins to think.",
    "me_room": "You sit back and listen to the gears in your head turn.",
    "actor_self": "$n holds $s chin in $s hand and begins to think to $mself...",
    "actor_other": "$n looks at $N and begins to grin like a pervert.",
    "actor_me": "$n looks at you and begins to think something really sick!",
    "me_actor": "You look at $N and begin to think nasty thoughts."
}